camiseta/Camiseta.py
camiseta/__init__.py
camiseta/info.py
camiseta/tag.py
camiseta/tempfile.py
camiseta/utils.py
camiseta-0.0.4.dist-info/LICENSE
camiseta-0.0.4.dist-info/METADATA
camiseta-0.0.4.dist-info/WHEEL
camiseta-0.0.4.dist-info/top_level.txt
camiseta-0.0.4.dist-info/RECORD
